opendlp/__init__.py
opendlp/regex_generation/__init__.py
opendlp/regex_generation/bpe.py
opendlp/regex_generation/dataset.py
opendlp/regex_generation/generator.py
opendlp/regex_generation/node_factory.py
opendlp/regex_generation/utils.py
opendlp/regex_generation/config/__init__.py
opendlp/regex_generation/config/conf.py
opendlp/regex_generation/config/evolve_param.py
opendlp/regex_generation/evolution/__init__.py
opendlp/regex_generation/evolution/evolve.py
opendlp/regex_generation/evolution/selection.py
opendlp/regex_generation/evolution/variation.py
opendlp/regex_generation/fitness/__init__.py
opendlp/regex_generation/fitness/fitness.py
opendlp/regex_generation/fitness/objective.py
opendlp/regex_generation/generations/__init__.py
opendlp/regex_generation/generations/dataset_population.py
opendlp/regex_generation/generations/population_init.py
opendlp/regex_generation/generations/random_population.py
opendlp/regex_generation/regex_tree/__init__.py
opendlp/regex_generation/regex_tree/id_factory.py
opendlp/regex_generation/regex_tree/node.py
opendlp/regex_generation/regex_tree/regex_context.py
opendlp/regex_generation/regex_tree/function_set/__init__.py
opendlp/regex_generation/regex_tree/function_set/backreference.py
opendlp/regex_generation/regex_tree/function_set/binary_operator.py
opendlp/regex_generation/regex_tree/function_set/concatenator.py
opendlp/regex_generation/regex_tree/function_set/group.py
opendlp/regex_generation/regex_tree/function_set/list_match.py
opendlp/regex_generation/regex_tree/function_set/list_not_match.py
opendlp/regex_generation/regex_tree/function_set/lookahead_negative.py
opendlp/regex_generation/regex_tree/function_set/lookahead_positive.py
opendlp/regex_generation/regex_tree/function_set/lookaround.py
opendlp/regex_generation/regex_tree/function_set/lookbehind_negative.py
opendlp/regex_generation/regex_tree/function_set/lookbehind_positive.py
opendlp/regex_generation/regex_tree/function_set/match_min_max.py
opendlp-0.1.1.dist-info/LICENSE
opendlp-0.1.1.dist-info/METADATA
opendlp-0.1.1.dist-info/WHEEL
opendlp-0.1.1.dist-info/top_level.txt
opendlp-0.1.1.dist-info/RECORD
