Metadata-Version: 2.1
Name: opendlp
Version: 0.1.1
Summary: openDLP
Home-page: https://github.com/hitsz-ids/openDLP
Author: histsz-ids
Author-email: 1337913069@qq.com
License: Apache License 2.0
Keywords: privacy,dlp,data-protection,data-loss-prevention,sensitive-data-discovery
Platform: UNKNOWN
Classifier: Development Status :: 2 - Pre-Alpha
Classifier: Intended Audience :: Developers
Classifier: Programming Language :: Python :: 3.6
Classifier: Programming Language :: Python :: 3.7
Classifier: Programming Language :: Python :: 3.8
Classifier: Programming Language :: Python :: 3.9
Classifier: License :: OSI Approved :: Apache Software License
Requires-Dist: tldextract (==3.1.2)
Requires-Dist: Ipy (==1.1)
Requires-Dist: pandas (==1.3.4)
Requires-Dist: torch (==1.10.0)
Requires-Dist: hanlp (==2.1.0a64)
Requires-Dist: pytest (==7.1.1)
